LICENSE
MANIFEST.in
README.rst
VERSION
setup.cfg
setup.py
tornado_opentracing/__init__.py
tornado_opentracing/_constants.py
tornado_opentracing/application.py
tornado_opentracing/handlers.py
tornado_opentracing/httpclient.py
tornado_opentracing/initialization.py
tornado_opentracing/tracing.py
tornado_opentracing.egg-info/PKG-INFO
tornado_opentracing.egg-info/SOURCES.txt
tornado_opentracing.egg-info/dependency_links.txt
tornado_opentracing.egg-info/requires.txt
tornado_opentracing.egg-info/top_level.txt