Metadata-Version: 1.1
Name: tornado-opentracing
Version: 1.0.1
Summary: OpenTracing support for Tornado applications
Home-page: https://github.com/opentracing-contrib/python-tornado/
Author: Carlos Alberto Cortez
Author-email: calberto.cortez@gmail.com
License: Apache License 2.0
Download-URL: https://github.com/opentracing-contrib/python-tornado/tarball/1.0.1
Platform: any
Classifier: Environment :: Web Environment
Classifier: Intended Audience :: Developers
Classifier: License :: OSI Approved :: BSD License
Classifier: Operating System :: OS Independent
Classifier: Programming Language :: Python
Classifier: Topic :: Internet :: WWW/HTTP :: Dynamic Content
Classifier: Topic :: Software Development :: Libraries :: Python Modules
